{"Exif":{"Lat":0,"Long":0,"Date":"2022-07-07T19:38:02+02:00","Tags":{"ApertureValue":6.33985,"BitsPerSample":[8,8,8],"CFAPattern":"","ColorSpace|int":"65535","ComponentsConfiguration":"","CompressedBitsPerPixel":4,"Contrast|int":"0","CustomRendered|int":"0","DateTimeDigitized|time.Time":"2022-07-07T19:38:02+02:00","DateTimeOriginal|time.Time":"2022-07-07T19:38:02+02:00","DateTime|time.Time":"2022-07-08T09:01:51+02:00","ExifIFDPointer|int":"432","ExifVersion":"0230","ExposureBiasValue|*big.Rat":"1/3","ExposureMode|int":"1","ExposureProgram|int":"1","ExposureTime|*big.Rat":"1/160","FNumber":9,"FileSource":"","FlashpixVersion":"0100","Flash|int":"0","FocalLength":70,"FocalLengthIn35mmFilm|int":"70","GPSInfoIFDPointer|int":"1140","GPSVersionID":[2,3,0,0],"GainControl|int":"1","ISOSpeedRatings|int":"2000","ImageLength|int":"3712","ImageWidth|int":"5568","InteroperabilityIFDPointer|int":"1108","InteroperabilityIndex":"R03","LightSource|int":"0","Make":"NIKON CORPORATION","MaxApertureValue":3,"MeteringMode|int":"3","Model":"NIKON D5","Orientation|int":"1","PhotometricInterpretation|int":"2","PixelXDimension|int":"5568","PixelYDimension|int":"3712","ResolutionUnit|int":"2","SamplesPerPixel|int":"3","Saturation|int":"0","SceneCaptureType|int":"0","SceneType":"","SensingMethod|int":"2","Sharpness|int":"2","ShutterSpeedValue":7.321928,"Software":"Adobe Photoshop CS6 (Windows)","SubSecTime":"06","SubSecTimeDigitized":"06","SubSecTimeOriginal":"06","SubjectDistanceRange|int":"0","ThumbJPEGInterchangeFormatLength|int":"9398","ThumbJPEGInterchangeFormat|int":"1254","UserComment":"ASCII","WhiteBalance|int":"0","XResolution":300,"YCbCrPositioning|int":"2","YResolution":300}}}
