{"Exif":{"Lat":0,"Long":0,"Date":"2023-08-01T14:47:52+02:00","Tags":{"ApertureValue":1.7962647457678684,"BrightnessValue|*imagemeta.rat[int32]":"439/100","ColorSpace|uint16":"65535","CreateDate":"2023:08:01 14:47:52","DateTimeOriginal":"2023:08:01 14:47:52","DigitalZoomRatio|*imagemeta.rat[uint32]":"1","ExifImageHeight|uint32":"3000","ExifImageWidth|uint32":"4000","ExifVersion":"0220","ExposureCompensation|*imagemeta.rat[int32]":"0","ExposureMode|uint16":"0","ExposureProgram|uint16":"2","ExposureTime|*imagemeta.rat[uint32]":"1/180","FNumber|*imagemeta.rat[uint32]":"9/5","Flash|uint16":"0","FocalLengthIn35mmFormat|uint16":"23","FocalLength|*imagemeta.rat[uint32]":"27/5","ISO|uint16":"80","ImageHeight|uint32":"3000","ImageUniqueID":"P12XLPE00CM","ImageWidth|uint32":"4000","Make":"samsung","MaxApertureValue":1.7962647457678684,"MeteringMode|uint16":"2","Model":"Galaxy S23","ModifyDate":"2023:08:01 14:47:52","OffsetTime":"+02:00","OffsetTimeOriginal":"+02:00","Orientation|uint16":"6","ResolutionUnit|uint16":"2","SceneCaptureType|uint16":"0","ShutterSpeedValue":0.9961565872205753,"Software":"S911BXXS3AWF7","SubSecTimeDigitized|int":"433","SubSecTimeOriginal|int":"433","SubSecTime|int":"433","WhiteBalance|uint16":"0","XResolution|*imagemeta.rat[uint32]":"72","YCbCrPositioning|uint16":"1","YResolution|*imagemeta.rat[uint32]":"72"}}}
